failsafe/__init__.py
failsafe/circuit_breaker.py
failsafe/failsafe.py
failsafe/fallback_failsafe.py
failsafe/retry_policy.py
pyfailsafe-0.1.1.dist-info/DESCRIPTION.rst
pyfailsafe-0.1.1.dist-info/METADATA
pyfailsafe-0.1.1.dist-info/RECORD
pyfailsafe-0.1.1.dist-info/WHEEL
pyfailsafe-0.1.1.dist-info/metadata.json
pyfailsafe-0.1.1.dist-info/top_level.txt
