Metadata-Version: 2.0
Name: pyfailsafe
Version: 0.1.1
Summary: Simple failure handling. Failsafe implementation in Python
Home-page: https://github.com/Skyscanner/pyfailsafe
Author: Skyscanner
Author-email: mshell@skyscanner.com
License: Apache
Platform: any
